{
  "grey": {
    "50": "#FCFDFD",
    "100": "#F9FAFB",
    "200": "#F4F6F8",
    "300": "#DFE3E8",
    "400": "#C4CDD5",
    "500": "#919EAB",
    "600": "#637381",
    "700": "#454F5B",
    "800": "#1C252E",
    "900": "#141A21"
  },
  "common": {
    "black": "#18181B",
    "white": "#FFFFFF"
  },
  "redDark": {
    "10": "#450303",
    "20": "#670909",
    "30": "#891313",
    "40": "#ab2020",
    "50": "#cd3030",
    "60": "#ef4444",
    "70": "#fe7171",
    "80": "#ff9a9a",
    "90": "#ffc4c4",
    "100": "#ffeded"
  },
  "redLight": {
    "10": "#ffeded",
    "20": "#ffc4c4",
    "30": "#ff9a9a",
    "40": "#fe7171",
    "50": "#ef4444",
    "60": "#cd3030",
    "70": "#ab2020",
    "80": "#891313",
    "90": "#670909",
    "100": "#450303"
  },
  "orangeDark": {
    "10": "#3b1b06",
    "20": "#7f3400",
    "30": "#a74500",
    "40": "#d05703",
    "50": "#f97316",
    "60": "#ff8e40",
    "70": "#ffa76a",
    "80": "#ffc094",
    "90": "#ffd8be",
    "100": "#fff1e8"
  },
  "orangeLight": {
    "10": "#fff1e8",
    "20": "#ffd8be",
    "30": "#ffc094",
    "40": "#ffa76a",
    "50": "#ff8e40",
    "60": "#f97316",
    "70": "#d05703",
    "80": "#a74500",
    "90": "#7f3400",
    "100": "#3b1b06"
  },
  "yellowDark": {
    "10": "#4f451c",
    "20": "#6c5f29",
    "30": "#897938",
    "40": "#a79349",
    "50": "#c4ae5b",
    "60": "#e1c96f",
    "70": "#fee584",
    "80": "#ffeda9",
    "90": "#ffff5c",
    "100": "#fffcf3"
  },
  "yellowLight": {
    "10": "#fffcf3",
    "20": "#ffff5c",
    "30": "#ffeda9",
    "40": "#fee584",
    "50": "#e1c96f",
    "60": "#c4ae5b",
    "70": "#a79349",
    "80": "#897938",
    "90": "#6c5f29",
    "100": "#4f451c"
  },
  "greenDark": {
    "10": "#004b2f",
    "20": "#036d46",
    "30": "#0d8f5f",
    "40": "#1ab179",
    "50": "#2bd395",
    "60": "#40f5b2",
    "70": "#6dffc9",
    "80": "#97ffd9",
    "90": "#c2ffe8",
    "100": "#ecfff8"
  },
  "greenLight": {
    "10": "#ecfff8",
    "20": "#c2ffe8",
    "30": "#97ffd9",
    "40": "#6dffc9",
    "50": "#40f5b2",
    "60": "#2bd395",
    "70": "#1ab179",
    "80": "#0d8f5f",
    "90": "#036d46",
    "100": "#004b2f"
  },
  "blueDark": {
    "10": "#002a4c",
    "20": "#004175",
    "30": "#00589d",
    "40": "#006fc6",
    "50": "#0387ef",
    "60": "#30a4ff",
    "70": "#5eb8ff",
    "80": "#8bccff",
    "90": "#b8e0ff",
    "100": "#e6f4ff"
  },
  "blueLight": {
    "10": "#e6f4ff",
    "20": "#b8e0ff",
    "30": "#8bccff",
    "40": "#5eb8ff",
    "50": "#30a4ff",
    "60": "#0387ef",
    "70": "#006fc6",
    "80": "#00589d",
    "90": "#004175",
    "100": "#002a4c"
  },
  "purpleDark": {
    "10": "#2a1b47",
    "20": "#3d2a64",
    "30": "#513982",
    "40": "#674b9f",
    "50": "#7d5ebc",
    "60": "#9573d9",
    "70": "#ae8af6",
    "80": "#cab0ff",
    "90": "#e1d2ff",
    "100": "#f7f4ff"
  },
  "purpleLight": {
    "10": "#f7f4ff",
    "20": "#e1d2ff",
    "30": "#cab0ff",
    "40": "#ae8af6",
    "50": "#9573d9",
    "60": "#7d5ebc",
    "70": "#674b9f",
    "80": "#513982",
    "90": "#3d2a64",
    "100": "#2a1b47"
  },
  "pinkDark": {
    "10": "#581646",
    "20": "#75225e",
    "30": "#932f77",
    "40": "#b03e91",
    "50": "#cd50ab",
    "60": "#ea63c5",
    "70": "#ff75d9",
    "80": "#ff9ee4",
    "90": "#ffc7f0",
    "100": "#fff1fb"
  },
  "pinkLight": {
    "10": "#fff1fb",
    "20": "#ffc7f0",
    "30": "#ff9ee4",
    "40": "#ff75d9",
    "50": "#ea63c5",
    "60": "#cd50ab",
    "70": "#b03e91",
    "80": "#932f77",
    "90": "#75225e",
    "100": "#581646"
  },
  "neutralDark": {
    "999": "#ffffff",
    "100": "#fdfdfd",
    "90": "#e7e8e9",
    "80": "#edecef",
    "70": "#d3d3db",
    "60": "#a1a1a8",
    "50": "#7a8397",
    "40": "#4d5a73",
    "30": "#222935",
    "20": "#262935",
    "10": "#1d1f28",
    "0": "#171920",
    "white": "#ffffff",
    "black": "#000000"
  },
  "neutralLight": {
    "999": "#020512",
    "100": "#0c111d",
    "90": "#121c2e",
    "80": "#374151",
    "70": "#666e7d",
    "60": "#818897",
    "50": "#a1a1a8",
    "40": "#d3d3db",
    "30": "#dfdfdf",
    "20": "#eff3f8",
    "10": "#f4f5f7",
    "0": "#ffffff",
    "white": "#ffffff",
    "black": "#000000"
  }
}
